netcheck/__init__.py
netcheck/cli.py
netcheck/context.py
netcheck/runner.py
netcheck/validation.py
netcheck/version.py
netcheck/checks/__init__.py
netcheck/checks/dns.py
netcheck/checks/http.py
netcheck/checks/internal.py
netcheck-0.5.6.dist-info/LICENSE
netcheck-0.5.6.dist-info/METADATA
netcheck-0.5.6.dist-info/WHEEL
netcheck-0.5.6.dist-info/entry_points.txt
netcheck-0.5.6.dist-info/top_level.txt
netcheck-0.5.6.dist-info/RECORD
