Metadata-Version: 2.2
Name: netcheck
Version: 0.5.6
Summary: Netchecks is a cloud native tool for specifying and regularly checking assertions about network conditions. Use netchecks to proactively verify whether security controls are working as intended, alerting on misconfiguration.
Author-email: Brian Thorne <brian@hardbyte.nz>
Requires-Python: <4.0,>=3.10
License-File: LICENSE
Requires-Dist: dnspython<3.0,>=2.2
Requires-Dist: requests<3.0,>=2.28
Requires-Dist: typer<1.0,>=0.9
Requires-Dist: pydantic<3.0,>=1.10
Requires-Dist: rich<14.0.0,>=10.11.0
Requires-Dist: cel-python<1.0.0,>=0.1.5
